{"cameraMode":{"drawMode":0,"name":"Shaded","section":"Shading Mode"},"sceneLighting":true,"audioPlay":false,"sceneViewState":{"m_AlwaysRefresh":false,"showFog":true,"showSkybox":true,"showFlares":true,"showImageEffects":true,"showParticleSystems":true,"showVisualEffectGraphs":true,"m_FxEnabled":true},"in2DMode":false,"pivot":{"x":2.384185791015625e-7,"y":0.0,"z":1.1920928955078126e-7},"rotation":{"x":-0.11642559617757797,"y":0.10171328485012055,"z":-0.011987060308456421,"w":-0.9879076480865479},"size":1.4028187990188599,"orthographic":false}